MANIFEST.in
pyproject.toml
setup.py
src/numerous.grpc.egg-info/PKG-INFO
src/numerous.grpc.egg-info/SOURCES.txt
src/numerous.grpc.egg-info/dependency_links.txt
src/numerous.grpc.egg-info/requires.txt
src/numerous.grpc.egg-info/top_level.txt
src/numerous/grpc/__init__.py
src/numerous/grpc/health_pb2.py
src/numerous/grpc/health_pb2.pyi
src/numerous/grpc/health_pb2_grpc.py
src/numerous/grpc/health_pb2_grpc.pyi
src/numerous/grpc/py.typed
src/numerous/grpc/spm_pb2.py
src/numerous/grpc/spm_pb2.pyi
src/numerous/grpc/spm_pb2_grpc.py
src/numerous/grpc/spm_pb2_grpc.pyi