Metadata-Version: 2.1
Name: numerous.grpc
Version: 1.1.0
Summary: Protocol buffers and gRPC implementation for numerous
Classifier: Operating System :: OS Independent
Classifier: Programming Language :: Python :: 3
Provides-Extra: generate
